pyanimalsay/__init__.py
pyanimalsay/animals.py
pyanimalsay/main.py
pyanimalsay-0.0.0.5.dist-info/entry_points.txt
pyanimalsay-0.0.0.5.dist-info/WHEEL
pyanimalsay-0.0.0.5.dist-info/METADATA
pyanimalsay-0.0.0.5.dist-info/RECORD
